json_schema_tool/__init__.py
json_schema_tool/coverage.py
json_schema_tool/exception.py
json_schema_tool/pointer.py
json_schema_tool/py.typed
json_schema_tool/schema.py
json_schema_tool/types.py
json_schema_tool-0.4.0.dist-info/LICENSE
json_schema_tool-0.4.0.dist-info/METADATA
json_schema_tool-0.4.0.dist-info/WHEEL
json_schema_tool-0.4.0.dist-info/entry_points.txt
json_schema_tool-0.4.0.dist-info/top_level.txt
json_schema_tool-0.4.0.dist-info/RECORD
