Metadata-Version: 2.1
Name: json_schema_tool
Version: 0.4.0
Summary: JSON Schema validation with various additional features
License: MIT License
Project-URL: Homepage, https://github.com/ifak/json_schema_tool
Keywords: python,json,json-schema
Classifier: License :: OSI Approved :: MIT License
Classifier: Programming Language :: Python
Classifier: Programming Language :: Python :: 3
Requires-Python: >=3.6
License-File: LICENSE
